src/__init__.py
src/main.py
src/api/__init__.py
src/api/answers.py
src/api/auth.py
src/api/companies.py
src/api/intelligence.py
src/api/metrics.py
src/api/refinitiv.py
src/api/reports.py
src/api/subscriptions.py
src/auth/__init__.py
src/auth/api_keys.py
src/auth/dependencies.py
src/billing/__init__.py
src/billing/lemonsqueezy_integration.py
src/data_sources/__init__.py
src/data_sources/aggregator.py
src/data_sources/alphavantage_source.py
src/data_sources/base.py
src/data_sources/finnhub_source.py
src/data_sources/market_data.py
src/data_sources/polygon_source.py
src/data_sources/sec_edgar.py
src/data_sources/yfinance_source.py
src/intelligence/insights_engine.py
src/intelligence/technical_indicators.py
src/middleware/__init__.py
src/middleware/auth.py
src/middleware/rate_limiter.py
src/models/__init__.py
src/models/user.py
cite_finance_mcp-0.1.4.dist-info/METADATA
cite_finance_mcp-0.1.4.dist-info/WHEEL
cite_finance_mcp-0.1.4.dist-info/entry_points.txt
cite_finance_mcp-0.1.4.dist-info/RECORD
