Metadata-Version: 2.4
Name: cite-finance-mcp
Version: 0.1.4
Summary: Financial Data MCP Server with Citations & Provenance
Author-email: Christopher Ongko <chris@cite-finance.io>
Requires-Python: >=3.10
Requires-Dist: httpx>=0.20.0
Requires-Dist: mcp>=0.1.0
Requires-Dist: starlette>=0.20.0
Requires-Dist: uvicorn>=0.20.0
